pylibbpf/__init__.py
pylibbpf/ir_to_ctypes.py
pylibbpf/py.typed
pylibbpf/pylibbpf.cpython-311-x86_64-linux-gnu.so
pylibbpf/wrappers.py
pylibbpf.libs/libbz2-a1e77c99.so.1.0.6
pylibbpf.libs/libelf-0-7210f05a.190.so
pylibbpf.libs/liblzma-51a76f52.so.5.2.4
pylibbpf.libs/libzstd-76b78bac.so.1.4.4
pylibbpf-0.0.6.dist-info/METADATA
pylibbpf-0.0.6.dist-info/WHEEL
pylibbpf-0.0.6.dist-info/top_level.txt
pylibbpf-0.0.6.dist-info/RECORD
pylibbpf-0.0.6.dist-info/licenses/LICENSE
