Metadata-Version: 2.4
Name: pylibbpf
Version: 0.0.6
Summary: Python Bindings for Libbpf
Home-page: https://github.com/pythonbpf/pylibbpf
Author: varun-r-mallya, r41k0u
Author-email: r41k0u <pragyanshchaturvedi18@gmail.com>, varun-r-mallya <varunrmallya@gmail.com>
License: 
Project-URL: Homepage, https://github.com/pythonbpf/pylibbpf
Project-URL: Repository, https://github.com/pythonbpf/pylibbpf
Project-URL: Issues, https://github.com/pythonbpf/pylibbpf/issues
Classifier: Development Status :: 3 - Alpha
Classifier: Intended Audience :: Developers
Classifier: Operating System :: POSIX :: Linux
Classifier: Programming Language :: Python :: 3
Classifier: Programming Language :: Python :: 3.8
Classifier: Programming Language :: Python :: 3.9
Classifier: Programming Language :: Python :: 3.10
Classifier: Programming Language :: Python :: 3.11
Classifier: Programming Language :: Python :: 3.12
Classifier: Programming Language :: C++
Classifier: Topic :: Software Development :: Libraries :: Python Modules
Classifier: Topic :: System :: Operating System Kernels :: Linux
Requires-Python: >=3.8
License-File: LICENSE
Requires-Dist: llvmlite>=0.40.0
Provides-Extra: test
Requires-Dist: pytest>=6.0; extra == "test"
Dynamic: author
Dynamic: home-page
Dynamic: license-file
Dynamic: requires-python
